jmxquery/JMXQuery-0.1.9.jar
jmxquery/__init__.py
jmxquery_jcruz-0.5.3.dist-info/LICENSE.txt
jmxquery_jcruz-0.5.3.dist-info/METADATA
jmxquery_jcruz-0.5.3.dist-info/WHEEL
jmxquery_jcruz-0.5.3.dist-info/top_level.txt
jmxquery_jcruz-0.5.3.dist-info/RECORD
