Metadata-Version: 2.1
Name: jmxquery-jcruz
Version: 0.5.3
Summary: A JMX Interface for Python to Query runtime metrics in a JVM
Home-page: https://github.com/outlyerapp/jmxquery
Author: Jonathan Cruz
Author-email: jcruzdeveloper@gmail.com
License: UNKNOWN
Keywords: java,jmx,metrics,monitoring
Platform: UNKNOWN
